kafka_cli/__init__.py
kafka_cli/__main__.py
kafka_cli/app.py
kafka_cli/Kafka/__init__.py
kafka_cli/Kafka/admin.py
kafka_cli/Kafka/base.py
kafka_cli/Kafka/consumer.py
kafka_cli/Kafka/producer.py
kafka_cli/cli/__init__.py
kafka_cli/cli/log.py
kafka_cli/cli/main.py
kafka_cli/cli/options.py
tests/__init__.py
tests/context.py
tests/test_consumer.py
tests/test_producer.py
pykafka_cli-1.2.0.dist-info/METADATA
pykafka_cli-1.2.0.dist-info/WHEEL
pykafka_cli-1.2.0.dist-info/dependency_links.txt
pykafka_cli-1.2.0.dist-info/entry_points.txt
pykafka_cli-1.2.0.dist-info/top_level.txt
pykafka_cli-1.2.0.dist-info/RECORD
